AUTHORS
LICENSE
MANIFEST.in
README.rst
setup.py
webcrawlers/__init__.py
webcrawlers/core.py
webcrawlers/http_headers.py
webcrawlers.egg-info/PKG-INFO
webcrawlers.egg-info/SOURCES.txt
webcrawlers.egg-info/dependency_links.txt
webcrawlers.egg-info/entry_points.txt
webcrawlers.egg-info/top_level.txt