Metadata-Version: 1.1
Name: webcrawlers
Version: 0.2.dev1
Summary: A collection of unofficial web APIs for Python
Home-page: http://www.jdhp.org/
Author: Jeremie DECOCK
Author-email: jd.jdhp@gmail.com
License: UNKNOWN
Download-URL: http://www.jdhp.org/
Keywords: web crawler
Platform: UNKNOWN
Classifier: Development Status :: 4 - Beta
Classifier: Intended Audience :: Developers
Classifier: License :: OSI Approved :: MIT License
Classifier: Natural Language :: English
Classifier: Operating System :: OS Independent
Classifier: Programming Language :: Python :: 3
Classifier: Topic :: Software Development :: Libraries
Classifier: Topic :: Software Development :: Libraries :: Python Modules
Classifier: Topic :: Software Development :: Libraries :: Application Frameworks
